{"Common Name": "Swiss cheese plant, Swiss cheese vine, five holes plant", "Botanical Name": "Monstera adansonii", "Family": "Araceae", "Plant Type": "Perennial", "Mature Size": "10\u201313 ft. tall (outdoors), 3\u20138 ft. tall (indoors), 1\u20133 ft. wide", "Sun Exposure": "Partial", "Soil Type": "Moist, well-drained", "Soil pH": "Acidic, neutral", "Bloom Time": "Spring (does not bloom indoors)", "Flower Color": "White", "Hardiness Zones": "10\u201312 (USDA)", "Native Area": "Central America, South America", "Toxicity": "Toxic to pets"}