{
    "Common Name": "Black Hills Spruce",
    "Botanical Name": "Picea glauca 'densata'",
    "Family Name": "Pinaceae",
    "Plant Type": "Coniferous Evergreen",
    "Mature Size": "20-25 Feet Tall 10-15 Feet Tall",
    "Sun Exposure": "Full Sun",
    "Soil Type": "Moist, well-drained",
    "Soil pH": "Acidic",
    "Bloom Time": "Non-flowering",
    "Flower Color": "Non-flowering",
    "Hardiness Zones": "USDA 3 to 6",
    "Native Area": "Black Hills of South Dakota",
    "image": "https://www.thespruce.com/thmb/nfzR7ZTaS1a_pQTlYEbum8vJkpQ=/1500x0/filters:no_upscale():max_bytes(150000):strip_icc():format(webp)/black-hills-spruce-growing-guide-5196340-hero-03d4cc0289c84df19de6d1adc952ac88.jpg"
}