{
    "Common Name": "Cardboard palm, cardboard plant, cardboard sago, cardboard cycad, Jamaican sago, Mexican cycad",
    "Botanical Name": "Zamia furfuracea",
    "Family": "Cycadaceae",
    "Plant Type": "Perennial",
    "Mature Size": "3\u20135 ft. tall, 4\u20136 ft. wide",
    "Sun Exposure": "Full",
    "Soil Type": "Sandy, well-drained",
    "Soil pH": "Acidic",
    "Bloom Time": "None",
    "Flower Color": "None",
    "Hardiness Zones": "9\u201311 (USDA)",
    "Native Area": "Central America",
    "Toxicity": "Toxic to people and pets",
    "image": "https://www.thespruce.com/thmb/qQV3TWk63oLJddeYIVxo4-Mds5M=/1500x0/filters:no_upscale():max_bytes(150000):strip_icc():format(webp)/grow-zamia-indoors-1902536-hero-482e41114ea84b37bf860086196ae6c0.jpg"
}