{
    "Botanical Name": "Brassica oleracea (Botrytis group)",
    "Common Name": "Cauliflower",
    "Plant Type": "Biennial, grown as an annual",
    "Mature Size": "12-30 in. tall, 12-24 in. wide",
    "Sun Exposure": "Full sun",
    "Soil Type": "Rich, well-draining",
    "Soil pH": "Neutral (6.5 to 7.5)",
    "Bloom Time": "Spring, fall",
    "Flower Color": "White, orange, purple, green",
    "Hardiness Zones": "2-11 (USDA)",
    "Native Area": "Europe",
    "image": "https://www.thespruce.com/thmb/qEWIWq9xltp1Cf6TgCbcw8alviA=/1500x0/filters:no_upscale():max_bytes(150000):strip_icc():format(webp)/how-to-grow-cauliflower-1403494-hero-76cf5f524a564adabb1ac6adfa311482.jpg"
}