{
    "Botanical Name": "Clematis Dr. Ruppel",
    "Common Name": "Dr. Ruppel clematis, Doctor Ruppel clematis, Dr. Ruppel virgin's bower",
    "Plant Type": "Deciduous perennial flowering vine",
    "Mature Size": "12 feet tall",
    "Sun Exposure": "Full sun to partial sun",
    "Soil Type": "Fertile, well-drained, and kept evenly moist",
    "Soil pH": "Neutral",
    "Bloom Time": "June",
    "Flower Color": "Pink",
    "Hardiness Zones": "4 to 8",
    "Native Area": "Several regions across both the Northern Hemisphere and Southern Hemisphere",
    "image": "https://www.thespruce.com/thmb/Xj1dfTtiAIfXpCEMqCkjQqqye-E=/1500x0/filters:no_upscale():max_bytes(150000):strip_icc():format(webp)/pink-clematis-flowers-dr-ruppel-4122498-hero-a74fafd653924ddd840a9666096ccec0.jpg"
}