{
    "Common Name": "Ivory silk lilac",
    "Botanical Name": "Syringa reticulata \u2018Ivory Silk\u2019",
    "Family Name": "Oleaceae",
    "Plant Type": "Tree or large shrub",
    "Mature Size": "20-30 ft. tall, 15-20 ft. wide",
    "Sun Exposure": "Full sun",
    "Soil Type": "Clays, sandy loams, well-draining",
    "Soil pH": "Neutral",
    "Bloom Time": "Late June/July",
    "Flower Color": "White",
    "Hardiness Zones": "USDA 3-7",
    "Native Area": "Japan",
    "image": "https://www.thespruce.com/thmb/p5JkS8dQm3vFkhxVcByMANOK3HE=/1500x0/filters:no_upscale():max_bytes(150000):strip_icc():format(webp)/grow-fatshedera-indoors-1902645-15-6d0b58adcfb443428a84baf629ca00aa.jpg"
}