{
    "Common Name": "Lemon verbena, lemon beebrush, vervain",
    "Botanical Name": "Aloysia citriodora",
    "Family": "Verbenaceae",
    "Plant Type": "Tender perennial in frost-free zones",
    "Mature Size": "6 ft. where hardy",
    "Sun Exposure": "Full sun",
    "Soil Type": "Rich and moist",
    "Soil pH": "Slightly acidic (6.1 to 7.0)",
    "Bloom Time": "Late summer",
    "Hardiness Zones": "8-11 (USDA)",
    "Native Area": "Argentina, Chile",
    "Toxicity": "Toxic to cats, dogs, and horses",
    "image": "https://www.thespruce.com/thmb/ATuaYvn8NpjY67QWhREsTyxkcqU=/1500x0/filters:no_upscale():max_bytes(150000):strip_icc():format(webp)/lenten-rose-plants-2132555-8-5d796e5162bf40b09dbd3b7503abce24.jpg"
}