{
    "Common Name": "Flapjack succulent, paddle plant, red pancakes, dessert cabbage",
    "Botanical Name": "Kalanchoe luciae",
    "Family": "Crassulaceae",
    "Plant Type": "Evergreen succulent",
    "Mature Size": "1-2 ft. tall, 2-3 ft. wide",
    "Sun Exposure": "Full, partial",
    "Soil Type": "Loamy, sandy, well-drained",
    "Soil pH": "Acidic, neutral, alkaline",
    "Bloom Time": "Spring",
    "Flower Color": "White with a tinge of yellow",
    "Hardiness Zones": "9-11 (USDA)",
    "Native Area": "South Africa",
    "Toxicity": "Toxic to people, toxic to pets",
    "image": "https://www.thespruce.com/thmb/ekIyvVHF_gARA0dMIlPOW0h9u-M=/1500x0/filters:no_upscale():max_bytes(150000):strip_icc():format(webp)/how-to-grow-pagoda-plants-507630601-3cd2df02974a49049a5830aad5d5ad3d.jpg"
}