{
    "Botanical Name": "Echinacea pallida",
    "Common Name": "Drooping coneflower, pale purple coneflower",
    "Plant Type": "Perennial",
    "Mature Size": "2-4 ft. tall, 1-2 ft. wide",
    "Sun Exposure": "Full",
    "Soil Type": "Well-drained",
    "Soil pH": "Neutral to acidic, alkaline",
    "Bloom Time": "Spring, summer",
    "Flower Color": "Pale pink, pale purple, white",
    "Hardiness Zones": "3-8 (USDA)",
    "Native Area": "North America",
    "image": "https://www.thespruce.com/thmb/-u4kM6AcD7_cwv3yL-5AERLRMFk=/1500x0/filters:no_upscale():max_bytes(150000):strip_icc():format(webp)/how-to-grow-pampas-grass-5194991-hero-d10eeb13dce544deae082032a9f2c167.jpg"
}