{
    "Common Name": "Purple leaf sand cherry, plum leaf sand cherry",
    "Botanical Name": "Prunus x cistena",
    "Family": "Rosaceae",
    "Plant Type": "Shrub",
    "Mature Size": "6\u201310 ft. tall, 5\u20138 ft. wide",
    "Sun Exposure": "Full",
    "Soil Type": "Moist, well-drained",
    "Soil pH": "Acidic, neutral",
    "Bloom Time": "Spring",
    "Flower Color": "Pink, white",
    "Hardiness Zones": "2\u20138 (USDA)",
    "Native Area": "North America",
    "image": "https://www.thespruce.com/thmb/FShOt3K1DixYWW_JFvQYCYrG0y8=/1500x0/filters:no_upscale():max_bytes(150000):strip_icc():format(webp)/fall-foliage-of-quaking-aspen-trees-2130926-hero-3b0841fb95104b328099b028b78921f3.jpg"
}