{
    "Common Name": "River birch, water birch, black bird, red birch",
    "Botanical Name": "Betula nigra",
    "Family": "Betulaceae",
    "Plant Type": "Tree",
    "Mature Size": "40\u201370 ft. tall, 40\u201360 ft. wide",
    "Sun Exposure": "Full, partial",
    "Soil Type": "Moist",
    "Soil pH": "Acidic",
    "Hardiness Zones": "4\u20139 (USDA)",
    "Native Area": "North America",
    "image": "https://www.thespruce.com/thmb/f--A2SMyGEUyCUV9ERwzEBrv9f4=/1500x0/filters:no_upscale():max_bytes(150000):strip_icc():format(webp)/rock-cotoneaster-plants-2132711-07-a56083b7be254c0a94f4671af5655166.jpg"
}