{
    "Botanical Name": "Actaea",
    "Common Names": "Bugbane,\u00a0white cohosh, snakeberry, doll's-eyes",
    "Family": "Ranunculaceae",
    "Plant Type": "Herbaceous, perennial",
    "Mature Size": "2-4 ft. tall (7 ft. tall with flowers)",
    "Sun Exposure": "Partial, shade",
    "Soil Type": "Well-drained",
    "Soil pH": "Neutral",
    "Bloom Time": "Summer, fall",
    "Flower Color": "White, lavender",
    "USDA Hardiness Zones": "4a-8a",
    "Native Area": "North America",
    "image": "https://www.thespruce.com/thmb/VJoeR_eHep5HBh1pmVga17i6nHQ=/1500x0/filters:no_upscale():max_bytes(150000):strip_icc():format(webp)/helenium-flowers-1316035-05-2a866c4ddd8349b99931bb49db9fb797.jpg"
}