{
    "Botanical Name": "Tulbaghia violacea",
    "Common Name": "Society Garlic, pink agapanthus",
    "Plant Type": "Tuberous blooming perennial",
    "Mature Size": "1 to 2 ft. tall",
    "Sun Exposure": "Full sun",
    "Soil Type": "Well-drained loam or light sandy soil",
    "Soil pH": "Neutral (6.8 to 7.5)",
    "Bloom Time": "Early summer to autumn",
    "Flower Color": "Lilac, lavender, pink",
    "Hardiness Zones": "7-10, USDA",
    "Native Area": "Eastern South Africa",
    "image": "https://www.thespruce.com/thmb/Rfh9LEAGomrvZJl9whW4Qio6aeE=/1500x0/filters:no_upscale():max_bytes(150000):strip_icc():format(webp)/how-to-grow-sorrel-4121351-hero-487b081edf2743ab8f2e931d50f61aee.jpg"
}