{
    "Common Name": "Solomon's seal",
    "Botanical Name": "Polygonatum spp.",
    "Family": "Asparagaceae",
    "Plant Type": "Herbaceous, perennial",
    "Mature Size": "6 in.\u20137 ft. tall, 1\u20134 ft. wide",
    "Sun Exposure": "Partial, shade",
    "Soil Type": "Moist, well-draining",
    "Soil pH": "Acidic, neutral",
    "Bloom Time": "Spring",
    "Flower Color": "White, green, pink",
    "Hardiness Zones": "3\u20139 (USDA)",
    "Native Area": "North America",
    "Toxicity": "Toxic to people., toxic to pets",
    "image": "https://www.thespruce.com/thmb/l-oCFGzA7h3irnFqp_BCzrgnT30=/1500x0/filters:no_upscale():max_bytes(150000):strip_icc():format(webp)/growing-sotol-plants-5089168-hero-1374612c4a0c421a9c48ed97b3f43464.jpg"
}