{
    "Common Name": "Spotted dead nettle, spotted henbit",
    "Botanical Name": "Lamium maculatum",
    "Family": "Lamiaceae",
    "Plant Type": "Herbaceous, perennial",
    "Mature Size": "6-9 in. tall, 12-24 in. wide",
    "Sun Exposure": "Shade, partial",
    "Soil Type": "Well-drained, loamy",
    "Soil pH": "Acidic",
    "Bloom Time": "Spring, summer",
    "Flower Color": "Pink, purple, white",
    "Hardiness Zones": "4-8 (USDA)",
    "Native Area": "Europe, Africa, Asia",
    "image": "https://www.thespruce.com/thmb/aq5OjUhLng94l9DvxeqSGezKdX0=/1500x0/filters:no_upscale():max_bytes(150000):strip_icc():format(webp)/GettyImages-975865582-f17fb7811f1f4603a2b2f4482ff97d97.jpg"
}