{
    "Common Name": "Common bean, green bean, French bean, snap bean, string bean",
    "Botanical Name": "Phaseolus vulgaris",
    "Family": "Fabaceae",
    "Plant Type": "Annual, vegetable",
    "Size": "2\u201315 ft. tall, 2\u20133 ft. wide",
    "Sun Exposure": "Full sun",
    "Soil Type": "Loamy, moist, well-drained",
    "Soil pH": "Acidic",
    "Hardiness Zones": "2\u201311 (USDA)",
    "Native Area": "South America, Central America",
    "Toxicity": "Toxic to people, toxic to pets",
    "image": "https://www.thespruce.com/thmb/R0H4Hdikdszmgw1spw4YO6SoY1Q=/1500x0/filters:no_upscale():max_bytes(150000):strip_icc():format(webp)/growing-string-of-dolphins-5089406-3-e7164cc797ab4560ac2ec88286a1316c.jpg"
}