{
    "Common Name": "Mountain cabbage tree, blue dracaena, toi, dracaena spikes",
    "Botanical Name": "Cordyline indivisa",
    "Family": "Lomandroideae",
    "Plant Type": "Evergreen tree",
    "Mature Size": "Up to 10-18 ft. tall",
    "Sun Exposure": "Partial shade",
    "Soil Type": "Moist, fertile, well-drained",
    "Soil pH": "Acidic",
    "Bloom Time": "Late spring/summer",
    "Flower Color": "White/green, purple/brown",
    "Hardiness Zones": "8-12 (USDA)",
    "Native Area": "New Zealand",
    "image": "https://www.thespruce.com/thmb/oOtvW0mwKmbKewp-Yddrx1YN5RM=/1500x0/filters:no_upscale():max_bytes(150000):strip_icc():format(webp)/graptoveria-topsy-debbie-plant-profile-4780515-10-1c95272e4fc64297b70297063d2252ca.jpg"
}