{
    "Common Names": "Topsy Debbi, lilac spoons",
    "Botanical Names": "x Graptoveria 'Topsy Debbi', x Graptoveria 'Lilac Spoons'",
    "Family": "Crassulaceae",
    "Plant Type": "Succulent",
    "Mature Size": "6 in. tall, 4 in. wide",
    "Sun Exposure": "Full",
    "Soil Type": "Sandy, well-drained",
    "Soil pH": "Acidic, neutral",
    "Bloom Time": "Spring",
    "Flower Color": "Yellow",
    "Hardiness Zones": "9-11 (USDA)",
    "Native Area": "Hybrid, no native range",
    "image": "https://www.thespruce.com/thmb/hxCg4-JMH1_WVu4n_HJNBfDIAps=/1500x0/filters:no_upscale():max_bytes(150000):strip_icc():format(webp)/growing-krantz-aloe-5094554-hero-5cbc040a148b4a7291e31c20a251ee6a.jpg"
}