{
    "Botanical Name": "Curcuma longa",
    "Common Name": "Turmeric, common turmeric, turmeric root",
    "Plant Type": "Herbaceous perennial",
    "Mature Size": "3 to 4 feet tall and wide",
    "Sun Exposure": "Full sun in the far North, partial sun elsewhere",
    "Soil Type": "Rich, well-drained, and consistently moist",
    "Soil pH": "Slightly\u00a0acidic\u00a0to slightly alkaline",
    "Bloom Time": "July to August",
    "Flower (Bract) Color": "Burgundy, green, pink, white, yellow, or bicolored",
    "USDA Plant Hardiness Zones": "8 to 11",
    "Native Area": "India and Malaysia",
    "image": "https://www.thespruce.com/thmb/Z49BibJJWgEPsL0xpuxW6KJwe7k=/1500x0/filters:no_upscale():max_bytes(150000):strip_icc():format(webp)/growing-tussock-sedge-5085289-hero-aa6362cdb3a74b53aeecab356ab2d76c.jpg"
}