{
    "Botanical Name": "Wasabia japonica",
    "Common Name": "Wasabi, Japanese horseradish",
    "Plant Type": "Perennial vegetable",
    "Size": "24 inches tall",
    "Sun Exposure": "Full shade",
    "Soil Type": "Moist, rich, well-drained",
    "Soil pH": "6.0\u20137.0 (slightly acidic to neutral)",
    "Hardiness Zones": "8\u201310 (USDA)",
    "Native Areas": "Japan",
    "image": "https://www.thespruce.com/thmb/ZjT3Xmaa2ZtMxAYfMBz0zBY5E2w=/1500x0/filters:no_upscale():max_bytes(150000):strip_icc():format(webp)/how-to-grow-watermelons-1403491-hero-2d1ce0752fed4ed599db3ba3b231f8b7.jpg"
}